maxwell/__init__.py
maxwell/actions.py
maxwell/sed.py
maxwell/train.py
maxwell/util.py
maxwell-0.2.6.dist-info/LICENSE.txt
maxwell-0.2.6.dist-info/METADATA
maxwell-0.2.6.dist-info/WHEEL
maxwell-0.2.6.dist-info/entry_points.txt
maxwell-0.2.6.dist-info/top_level.txt
maxwell-0.2.6.dist-info/RECORD
