Metadata-Version: 2.1
Name: maxwell
Version: 0.2.6
Summary: Stochastic Edit Distance aligner for string transduction
Author: Simon Clematide, Peter Makarov, Travis Bartley
License: Apache 2.0
Project-URL: homepage, https://github.com/CUNY-CL/maxwell
Keywords: computational linguistics,morphology,natural language processing,language
Classifier: Programming Language :: Python :: 3.9
Classifier: Programming Language :: Python :: 3.10
Classifier: Programming Language :: Python :: 3.11
Classifier: Programming Language :: Python :: 3.12
Classifier: Programming Language :: Python :: 3.13
Classifier: Development Status :: 4 - Beta
Classifier: Environment :: Console
Classifier: License :: OSI Approved :: Apache Software License
Classifier: Operating System :: OS Independent
Classifier: Topic :: Text Processing :: Linguistic
Requires-Python: >=3.9
License-File: LICENSE.txt
Requires-Dist: numpy>=1.20.1
Requires-Dist: tqdm>=4.64.1
